cmflow/__init__.py
cmflow/conceptual_models.py
cmflow/geom_3dface_utils.py
cmflow/geom_surface_utils.py
cmflow/schema_wet_surface_features.json
cmflow/t2data_utils.py
cmflow/test_conceptual_models.py
cmflow/test_geom_3dface_utils.py
cmflow/test_geom_3dface_utils_ex.ts
cmflow/test_geom_3dface_utils_geom.dat
cmflow/test_geom_surface_utils.py
cmflow-0.1.1.dev57.dist-info/AUTHORS
cmflow-0.1.1.dev57.dist-info/METADATA
cmflow-0.1.1.dev57.dist-info/WHEEL
cmflow-0.1.1.dev57.dist-info/pbr.json
cmflow-0.1.1.dev57.dist-info/top_level.txt
cmflow-0.1.1.dev57.dist-info/RECORD
