Metadata-Version: 2.1
Name: cmflow
Version: 0.1.1.dev57
Summary: Building TOUGH2/Waiwera models from layers of conceptual models
Home-page: http://pypi.python.org/pypi/cmflow
Author: Angus Yeh
Author-email: a.yeh@auckland.ac.nz
License: LGPLv3
Platform: UNKNOWN
Classifier: Programming Language :: Python :: 2
Classifier: License :: OSI Approved :: GNU Lesser General Public License v3 (LGPLv3)
Classifier: Operating System :: OS Independent
